LICENSE.txt
MANIFEST.in
README.md
requirements.txt
setup.cfg
setup.py
QuickBPE/__init__.py
QuickBPE/base.py
QuickBPE/basic.py
QuickBPE/regexFast.py
QuickBPE.egg-info/PKG-INFO
QuickBPE.egg-info/SOURCES.txt
QuickBPE.egg-info/dependency_links.txt
QuickBPE.egg-info/requires.txt
QuickBPE.egg-info/top_level.txt
QuickBPE/fastfuncs/__init__.py
QuickBPE/fastfuncs/funcs.py